README.md
setup.py
dialogbot/__init__.py
dialogbot/bot.py
dialogbot/config.py
dialogbot.egg-info/PKG-INFO
dialogbot.egg-info/SOURCES.txt
dialogbot.egg-info/dependency_links.txt
dialogbot.egg-info/requires.txt
dialogbot.egg-info/top_level.txt
dialogbot/../CONTRIBUTING.md
dialogbot/../LICENSE
dialogbot/../README.md
dialogbot/../README_en.md
dialogbot/../requirements.txt
dialogbot/data/medical_sample.json
dialogbot/data/punctuations.txt
dialogbot/data/remove_words.txt
dialogbot/data/stopwords.txt
dialogbot/data/total_ware.txt
dialogbot/data/user_define_words.txt
dialogbot/data/medical_dict/check.txt
dialogbot/data/medical_dict/deny.txt
dialogbot/data/medical_dict/department.txt
dialogbot/data/medical_dict/disease.txt
dialogbot/data/medical_dict/drug.txt
dialogbot/data/medical_dict/food.txt
dialogbot/data/medical_dict/producer.txt
dialogbot/data/medical_dict/symptom.txt
dialogbot/data/person_graph/README.md
dialogbot/data/person_graph/big_rel_distribution.txt
dialogbot/data/person_graph/person_rel_kg.txt
dialogbot/data/person_graph/small_rel_distribution.txt
dialogbot/data/taobao/context_response.txt
dialogbot/data/taobao/dev.txt
dialogbot/data/taobao/process.py
dialogbot/data/taobao/question_answer.txt
dialogbot/data/taobao/test.txt
dialogbot/data/taobao/vocab.txt
dialogbot/gpt/__init__.py
dialogbot/gpt/data_parallel.py
dialogbot/gpt/earlystop.py
dialogbot/gpt/generate_subset.py
dialogbot/gpt/gptbot.py
dialogbot/gpt/interact.py
dialogbot/gpt/preprocess.py
dialogbot/gpt/train.py
dialogbot/kg/__init__.py
dialogbot/kg/answer_searcher.py
dialogbot/kg/bot.py
dialogbot/kg/question_classifier.py
dialogbot/kg/question_parser.py
dialogbot/kg/preprocess/__init__.py
dialogbot/kg/preprocess/build_medicalgraph.py
dialogbot/kg/preprocess/data_2_db.py
dialogbot/kg/preprocess/data_spider.py
dialogbot/reader/__init__.py
dialogbot/reader/corpus.py
dialogbot/reader/data_helper.py
dialogbot/search/__init__.py
dialogbot/search/searchbot.py
dialogbot/search/internet/__init__.py
dialogbot/search/internet/html_crawler.py
dialogbot/search/internet/search_engine.py
dialogbot/search/local/__init__.py
dialogbot/search/local/bm25model.py
