Metadata-Version: 2.1
Name: dialogbot
Version: 0.1.3
Summary: Dialog Robot, ChatBot
Home-page: https://github.com/shibing624/dialogbot
Author: XuMing
Author-email: xuming624@qq.com
License: Apache 2.0
Keywords: NLP,chatbot,dialogbot,dialogue,dialog
Platform: UNKNOWN
Classifier: Intended Audience :: Developers
Classifier: Operating System :: OS Independent
Classifier: Natural Language :: Chinese (Simplified)
Classifier: Natural Language :: Chinese (Traditional)
Classifier: Programming Language :: Python
Classifier: Programming Language :: Python :: 3
Classifier: Topic :: Text Processing
Classifier: Topic :: Text Processing :: Indexing
Classifier: Topic :: Text Processing :: Linguistic
